LICENSE
MANIFEST.in
README.md
README.rst
data.json
pyproject.toml
setup.cfg
setup.py
districts/__init__.py
districts/admin.py
districts/apps.py
districts/models.py
districts/serializers.py
districts/tests.py
districts/urls.py
districts/views.py
districts/management/__init__.py
districts/management/commands/__init__.py
districts/management/commands/load_districts_data.py
districts/migrations/0001_initial.py
districts/migrations/__init__.py
django_districts.egg-info/PKG-INFO
django_districts.egg-info/SOURCES.txt
django_districts.egg-info/dependency_links.txt
django_districts.egg-info/requires.txt
django_districts.egg-info/top_level.txt